python_pangu/__init__.py
python_pangu/gateway_base/__init__.py
python_pangu/gateway_base/gateway_base.py
python_pangu/gateway_base_aio/__init__.py
python_pangu/gateway_base_aio/gateway_base_aio.py
python_pangu/pangu_base/__init__.py
python_pangu/pangu_base/banyan_base.py
python_pangu/pangu_base_aio/__init__.py
python_pangu/pangu_base_aio/pangu_base_aio.py
python_pangu-0.0.8.dist-info/LICENSE
python_pangu-0.0.8.dist-info/METADATA
python_pangu-0.0.8.dist-info/WHEEL
python_pangu-0.0.8.dist-info/top_level.txt
python_pangu-0.0.8.dist-info/RECORD
