Metadata-Version: 2.1
Name: python-pangu
Version: 0.0.8
Summary: ai adapter client for python
Home-page: https://gitee.com/GokGok_group/python-pangu
Author: championchangpeng
Author-email: championchangpeng@gmail.com
License: UNKNOWN
Keywords: python pangu,RPC,Remote Procedure Call,Event Driven,Asynchronous,Non-Blocking,Raspberry Pi,ZeroMQ,MessagePack,Arduino
Platform: UNKNOWN
Classifier: Development Status :: 5 - Production/Stable
Classifier: Environment :: Other Environment
Classifier: Intended Audience :: Education
Classifier: Intended Audience :: Developers
Classifier: License :: OSI Approved :: GNU Affero General Public License v3 or later (AGPLv3+)
Classifier: Operating System :: OS Independent
Classifier: Programming Language :: Python :: 2.7
Classifier: Programming Language :: Python :: 3.4
Classifier: Programming Language :: Python :: 3.5
Classifier: Topic :: Education
Classifier: Topic :: Software Development
Classifier: Topic :: Software Development :: Libraries :: Application Frameworks
Classifier: Topic :: System :: Hardware
Requires-Dist: pyzmq
Requires-Dist: msgpack-python
Requires-Dist: psutil
